{"uri":"http://172.29.100.36:8080/OCDSWS/rest/ocid/ocds-07smqs-1320473","version":"1.1","extensions":["https://raw.githubusercontent.com/CompraNet/ocds_releasePublisher_extension/master/extension.json","https://raw.githubusercontent.com/CompraNet/ocds_schemeUrl_extension/master/extension.json","https://raw.githubusercontent.com/CompraNet/ocds_cycle_extension/master/extension.json"],"publishedDate":"2018-11-12T14:14:50Z","publicationPolicy":"https://compranetinfo.funcionpublica.gob.mx/descargas/politica-publicacion-EDCA-MX.pdf","releases":[{"publisher":{"uid":"27511","name":"SECRETARÍA DE LA FUNCIÓN PÚBLICA","uri":"http://www.gob.mx/sfp"},"cycle":2017,"ocid":"ocds-07smqs-1320473","id":"SFP-1320473-2018-11-12","date":"2017-04-03T10:51:27Z","tag":["tender","award"],"initiationType":"tender","parties":[{"name":"Secretaría de la Función Pública","id":"SFP-270","roles":["buyer"]},{"name":"SFP-Dirección General de Recursos Materiales y Servicios Generales #027000002","id":"SFP941229IMA-027000002","identifier":{"id":"SFP941229IMA-027000002","legalName":"SFP-Dirección General de Recursos Materiales y Servicios Generales #027000002","scheme":"MX-RFC","uri":"https://portalsat.plataforma.sat.gob.mx/ConsultaRFC"},"address":{"streetAddress":"Insurgentes Sur 1735 mezzanine ala sur colonia Guadalupe Inn","locality":"Álvaro Obregón","region":"Ciudad de México","postalCode":"1020","countryName":"MX"},"contactPoint":{"name":"Antonio Omar Fragoso Rodríguez","email":"afragoso@funcionpublica.gob.mx","telephone":"2000-3000 ext 5027"},"roles":["procuringEntity"]},{"name":"RAFAEL ALFONSO CASTRO LOPEZ","id":"9AB7B14ADBEEB2B975503A16F8D8F16C","identifier":{"id":"9AB7B14ADBEEB2B975503A16F8D8F16C","legalName":"RAFAEL ALFONSO CASTRO LOPEZ","scheme":"MX-RFC","uri":"https://portalsat.plataforma.sat.gob.mx/ConsultaRFC"},"address":{"streetAddress":"CALLE 32 MZ 22 LOTE 82 A VILLA DE GUADALUPE XALOSTOC","locality":"ECATEPEC ","region":"MX-MEX","postalCode":"55339","countryName":"MÉXICO"},"contactPoint":{"name":"RAFAEL ALFONSO CASTRO LOPEZ","email":"castrolr78@hotmail.com","telephone":"38718300 EXT. 20133"},"roles":["tenderer","supplier"]}],"buyer":{"name":"Secretaría de la Función Pública","id":"SFP-270"},"tender":{"id":"1320473","title":"APOYO EN LA PRÁCTICA DE AUDITORÍAS POR LA UNIDAD DE AUDITORÍA GUBERNAMENTAL","description":"SERVICIOS DE APOYO EN LA PRÁCTICA DE AUDITORÍAS Y/O VISITAS DE INSPECCIÓN Y/O SEGUIMIENTOS QUE REALICE LA UNIDAD DE AUDITORÍA GUBERNAMENTAL, POR SI O EN COORDINACIÓN CON OTRAS ÁREAS DE LA SECRETARÍA DE LA FUNCIÓN PÚBLICA, A LAS DEPENDENCIAS Y ENTIDADES DE LA ADMINISTRACIÓN PÚBLICA FEDERAL Y A LA PROCURADURÍA GENERAL DE LA REPÚBLICA, ASÍ COMO A FIDEICOMISOS PÚBLICOS NO PARAESTATALES, MANDATOS Y CONTRATOS ANÁLOGOS; APOYO EN LA REVISIÓN Y, EN SU CASO, INTEGRACIÓN DE LOS EXPEDIENTES DE LA INFORMACIÓN GENERADA COMO RESULTADO DE ÉSTAS, CORRESPONDIENTES AL PROGRAMA ANUAL DE TRABAJO 2017 O LAS QUE INSTRUYA EL TITULAR DE LA UNIDAD DE AUDITORÍA GUBERNAMENTAL, O APOYO EN ACTIVIDADES GUBERNAMENTALES; ASÍ TAMBIÉN APOYO EN LA ELABORACIÓN DE PROYECTOS DE DENUNCIAS Y/O DE INFORMES E INTEGRACIÓN DE EXPEDIENTES DE PRESUNTA RESPONSABILIDAD QUE SE LE ENCOMIENDEN, LOS CUALES SERÁN PAGADOS CON RECURSOS DEL DERECHO DEL 5 AL MILLAR, EN TÉRMINOS DEL ARTÍCULO 191 DE LA LEY FEDERAL DE DERECHOS\r\n","status":"complete","procuringEntity":{"name":"SFP-Dirección General de Recursos Materiales y Servicios Generales #027000002","id":"SFP941229IMA-027000002"},"items":[],"value":{"amount":0.0},"procurementMethod":"direct","procurementMethodRationale":"Art. 41 fr. XIV","submissionMethod":["inPerson"],"tenderPeriod":{"startDate":"2017-04-03T10:51:27Z"},"enquiryPeriod":{"startDate":"2017-04-03T10:51:27Z"},"hasEnquiries":false,"awardPeriod":{"endDate":"2016-12-26T00:00:00Z"}},"language":"es","awards":[{"id":"1378432","title":"APOYO EN LA PRÁCTICA DE AUDITORÍAS POR LA UNIDAD DE AUDITORÍA GUBERNAMENTAL","description":"SERVICIOS DE APOYO EN LA PRÁCTICA DE AUDITORÍAS Y/O VISITAS DE INSPECCIÓN Y/O SEGUIMIENTOS QUE REALICE LA UNIDAD DE AUDITORÍA GUBERNAMENTAL, POR SI O EN COORDINACIÓN CON OTRAS ÁREAS DE LA SECRETARÍA DE LA FUNCIÓN PÚBLICA, A LAS DEPENDENCIAS Y ENTIDADES DE LA ADMINISTRACIÓN PÚBLICA FEDERAL Y A LA PROCURADURÍA GENERAL DE LA REPÚBLICA, ASÍ COMO A FIDEICOMISOS PÚBLICOS NO PARAESTATALES, MANDATOS Y CONTRATOS ANÁLOGOS; APOYO EN LA REVISIÓN Y, EN SU CASO, INTEGRACIÓN DE LOS EXPEDIENTES DE LA INFORMACIÓN GENERADA COMO RESULTADO DE ÉSTAS, CORRESPONDIENTES AL PROGRAMA ANUAL DE TRABAJO 2017 O LAS QUE INSTRUYA EL TITULAR DE LA UNIDAD DE AUDITORÍA GUBERNAMENTAL, O APOYO EN ACTIVIDADES GUBERNAMENTALES; ASÍ TAMBIÉN APOYO EN LA ELABORACIÓN DE PROYECTOS DE DENUNCIAS Y/O DE INFORMES E INTEGRACIÓN DE EXPEDIENTES DE PRESUNTA RESPONSABILIDAD QUE SE LE ENCOMIENDEN, LOS CUALES SERÁN PAGADOS CON RECURSOS DEL DERECHO DEL 5 AL MILLAR, EN TÉRMINOS DEL ARTÍCULO 191 DE LA LEY FEDERAL DE DERECHOS\r\n","status":"active","value":{"amount":532256.89,"currency":"MXN"},"suppliers":[{"name":"RAFAEL ALFONSO CASTRO LOPEZ","id":"9AB7B14ADBEEB2B975503A16F8D8F16C"}],"contractPeriod":{"startDate":"2017-01-19T09:00:00Z","endDate":"2017-12-20T11:59:00Z"}}],"contracts":[{"id":1378432,"awardID":"1378432","title":"APOYO EN LA PRÁCTICA DE AUDITORÍAS POR LA UNIDAD DE AUDITORÍA GUBERNAMENTAL","description":"SERVICIOS DE APOYO EN LA PRÁCTICA DE AUDITORÍAS Y/O VISITAS DE INSPECCIÓN Y/O SEGUIMIENTOS QUE REALICE LA UNIDAD DE AUDITORÍA GUBERNAMENTAL, POR SI O EN COORDINACIÓN CON OTRAS ÁREAS DE LA SECRETARÍA DE LA FUNCIÓN PÚBLICA, A LAS DEPENDENCIAS Y ENTIDADES DE LA ADMINISTRACIÓN PÚBLICA FEDERAL Y A LA PROCURADURÍA GENERAL DE LA REPÚBLICA, ASÍ COMO A FIDEICOMISOS PÚBLICOS NO PARAESTATALES, MANDATOS Y CONTRATOS ANÁLOGOS; APOYO EN LA REVISIÓN Y, EN SU CASO, INTEGRACIÓN DE LOS EXPEDIENTES DE LA INFORMACIÓN GENERADA COMO RESULTADO DE ÉSTAS, CORRESPONDIENTES AL PROGRAMA ANUAL DE TRABAJO 2017 O LAS QUE INSTRUYA EL TITULAR DE LA UNIDAD DE AUDITORÍA GUBERNAMENTAL, O APOYO EN ACTIVIDADES GUBERNAMENTALES; ASÍ TAMBIÉN APOYO EN LA ELABORACIÓN DE PROYECTOS DE DENUNCIAS Y/O DE INFORMES E INTEGRACIÓN DE EXPEDIENTES DE PRESUNTA RESPONSABILIDAD QUE SE LE ENCOMIENDEN, LOS CUALES SERÁN PAGADOS CON RECURSOS DEL DERECHO DEL 5 AL MILLAR, EN TÉRMINOS DEL ARTÍCULO 191 DE LA LEY FEDERAL DE DERECHOS\r\n","status":"terminated","period":{"startDate":"2017-01-19T09:00:00Z","endDate":"2017-12-20T11:59:00Z"},"value":{"amount":532256.89,"currency":"MXN"},"dateSigned":"2017-01-30T00:00:00Z"}]}],"publisher":{"uid":"27511","name":"SECRETARÍA DE LA FUNCIÓN PÚBLICA","uri":"http://www.gob.mx/sfp"}}