{"uri":"http://172.29.100.36:8080/OCDSWS/rest/ocid/ocds-07smqs-1340321","version":"1.1","extensions":["https://raw.githubusercontent.com/CompraNet/ocds_releasePublisher_extension/master/extension.json","https://raw.githubusercontent.com/CompraNet/ocds_schemeUrl_extension/master/extension.json","https://raw.githubusercontent.com/CompraNet/ocds_cycle_extension/master/extension.json"],"publishedDate":"2018-11-12T14:17:37Z","publicationPolicy":"https://compranetinfo.funcionpublica.gob.mx/descargas/politica-publicacion-EDCA-MX.pdf","releases":[{"publisher":{"uid":"27511","name":"SECRETARÍA DE LA FUNCIÓN PÚBLICA","uri":"http://www.gob.mx/sfp"},"cycle":2017,"ocid":"ocds-07smqs-1340321","id":"SFP-1340321-2018-11-12","date":"2017-04-24T01:39:20Z","tag":["tender","award"],"initiationType":"tender","parties":[{"name":"Agencia de Servicios a la Comercialización y Desarrollo de Mercados Agropecuarios","id":"ASERCA-24","roles":["buyer"]},{"name":"ASERCA-APOYOS Y SERVICIOS A LA COMERCIALIZACION AGROPECUARIA 2 #008F00004","id":"ASC910416PK9-008F00004","identifier":{"id":"ASC910416PK9-008F00004","legalName":"ASERCA-APOYOS Y SERVICIOS A LA COMERCIALIZACION AGROPECUARIA 2 #008F00004","scheme":"MX-RFC","uri":"https://portalsat.plataforma.sat.gob.mx/ConsultaRFC"},"address":{"streetAddress":"CALLE 2-A N0.401 ENTRE 1 AV. Y 128-B COL. DIAZ ORDAZ","locality":"Mérida","region":"Yucatán","postalCode":"97130","countryName":"MX"},"contactPoint":{"name":"MANUEL MASSA RAMOS","email":"manuel.massa@aserca.gob.mx","telephone":"9999430167"},"roles":["procuringEntity"]},{"name":"KENIA MARYTERE PERERA SANCHEZ","id":"F7D16092001ECB7C42F845B553E6F4F1","identifier":{"id":"F7D16092001ECB7C42F845B553E6F4F1","legalName":"KENIA MARYTERE PERERA SANCHEZ","scheme":"MX-RFC","uri":"https://portalsat.plataforma.sat.gob.mx/ConsultaRFC"},"address":{"streetAddress":"calle 67G #323 por 128 B y 130 BOSQUES DE YUCATLPETEN","locality":"Mérida","region":"MX-YUC","postalCode":"97246","countryName":"MÉXICO"},"contactPoint":{"name":"kenia perera sanchez","email":"ing.keniaperera@outlook.com","telephone":"5219992762449"},"roles":["tenderer","supplier"]}],"buyer":{"name":"Agencia de Servicios a la Comercialización y Desarrollo de Mercados Agropecuarios","id":"ASERCA-24"},"tender":{"id":"1340321","title":"PRESTACION DE SERVICIOS PROFESIONALES","description":"PRESTACIÓN DE SERVICIOS DE APOYO EN LA OPERACIÓN DEL PROGRAMA DE COMERCIALIZACIÓN\r\n\r\n","status":"complete","procuringEntity":{"name":"ASERCA-APOYOS Y SERVICIOS A LA COMERCIALIZACION AGROPECUARIA 2 #008F00004","id":"ASC910416PK9-008F00004"},"items":[],"value":{"amount":0.0},"procurementMethod":"direct","procurementMethodRationale":"Art. 41 fr. XIV","submissionMethod":["written"],"tenderPeriod":{"startDate":"2017-04-24T01:39:20Z"},"enquiryPeriod":{"startDate":"2017-04-24T01:39:20Z"},"hasEnquiries":false,"awardPeriod":{"endDate":"2017-04-17T00:00:00Z"}},"language":"es","awards":[{"id":"1402095","title":"PRESTACION DE SERVICIOS PROFESIONALES","description":"PRESTACIÓN DE SERVICIOS DE APOYO EN LA OPERACIÓN DEL PROGRAMA DE COMERCIALIZACIÓN\r\n\r\n","status":"active","value":{"amount":131896.56,"currency":"MXN"},"suppliers":[{"name":"KENIA MARYTERE PERERA SANCHEZ","id":"F7D16092001ECB7C42F845B553E6F4F1"}],"contractPeriod":{"startDate":"2017-04-19T12:00:00Z","endDate":"2017-12-20T11:59:00Z"}}],"contracts":[{"id":1402095,"awardID":"1402095","title":"PRESTACION DE SERVICIOS PROFESIONALES","description":"PRESTACIÓN DE SERVICIOS DE APOYO EN LA OPERACIÓN DEL PROGRAMA DE COMERCIALIZACIÓN\r\n\r\n","status":"terminated","period":{"startDate":"2017-04-19T12:00:00Z","endDate":"2017-12-20T11:59:00Z"},"value":{"amount":131896.56,"currency":"MXN"},"dateSigned":"2017-04-19T00:00:00Z"}]}],"publisher":{"uid":"27511","name":"SECRETARÍA DE LA FUNCIÓN PÚBLICA","uri":"http://www.gob.mx/sfp"}}