{"uri":"http://172.29.100.36:8080/OCDSWS/rest/ocid/ocds-07smqs-1640007","version":"1.1","extensions":["https://raw.githubusercontent.com/CompraNet/ocds_releasePublisher_extension/master/extension.json","https://raw.githubusercontent.com/CompraNet/ocds_schemeUrl_extension/master/extension.json","https://raw.githubusercontent.com/CompraNet/ocds_cycle_extension/master/extension.json"],"publishedDate":"2018-11-12T14:44:51Z","publicationPolicy":"https://compranetinfo.funcionpublica.gob.mx/descargas/politica-publicacion-EDCA-MX.pdf","releases":[{"publisher":{"uid":"27511","name":"SECRETARÍA DE LA FUNCIÓN PÚBLICA","uri":"http://www.gob.mx/sfp"},"cycle":2018,"ocid":"ocds-07smqs-1640007","id":"SFP-1640007-2018-11-12","date":"2018-03-14T06:04:40Z","tag":["tender","award"],"initiationType":"tender","parties":[{"name":"Secretaría de Medio Ambiente y Recursos Naturales","id":"SEMARNAT-273","roles":["buyer"]},{"name":"SEMARNAT-Dirección de Adquisiciones y Contratos #016000997","id":"SMA941228GU8-016000997","identifier":{"id":"SMA941228GU8-016000997","legalName":"SEMARNAT-Dirección de Adquisiciones y Contratos #016000997","scheme":"MX-RFC","uri":"https://portalsat.plataforma.sat.gob.mx/ConsultaRFC"},"address":{"streetAddress":"Ejército Nacional No. 223, Col. Anáhuac","locality":"Miguel Hidalgo","region":"Ciudad de México","postalCode":"11350","countryName":"MX"},"contactPoint":{"name":"Elvia Patricia Bañuelos Solano","email":"patricia.banuelo@semarnat.gob.mx","telephone":"55 56280600 ext. 25848"},"roles":["procuringEntity"]},{"name":"NOTMUSA SA DE CV","id":"NOT011226T29","identifier":{"id":"NOT011226T29","legalName":"NOTMUSA SA DE CV","scheme":"MX-RFC","uri":"https://portalsat.plataforma.sat.gob.mx/ConsultaRFC"},"address":{"streetAddress":"PERIFERICO SUR 4293, JARDINES EN LA MONTAÑA","locality":"TLALPAN","region":"MX-CMX","postalCode":"14210","countryName":"MÉXICO"},"contactPoint":{"name":"CARLOS MANUEL  FLORES NUÑEZ","email":"jhernandez@notmusa.com.mx; ","telephone":"91 40 95 00"},"roles":["tenderer","supplier"]}],"buyer":{"name":"Secretaría de Medio Ambiente y Recursos Naturales","id":"SEMARNAT-273"},"tender":{"id":"1640007","title":"SERVICIOS DE DIFUSIÓN DE LA CAMPAÑA \"CONTAMINACIÓN AMBIENTAL\"","description":"CONTRATACIÓN DE LOS SERVICIOS DE DIFUSIÓN DE LA CAMPAÑA \"CONTAMINACIÓN AMBIENTAL\"","status":"complete","procuringEntity":{"name":"SEMARNAT-Dirección de Adquisiciones y Contratos #016000997","id":"SMA941228GU8-016000997"},"items":[],"value":{"amount":0.0},"procurementMethod":"direct","procurementMethodRationale":"Art. 41 fr. V","submissionMethod":["inPerson"],"tenderPeriod":{"startDate":"2018-03-14T06:04:40Z"},"enquiryPeriod":{"startDate":"2018-03-14T06:04:40Z"},"hasEnquiries":false,"awardPeriod":{"endDate":"2017-05-04T00:00:00Z"}},"language":"es","awards":[{"id":"1746626","title":"CONTRATACIÓN DE LOS SERVICIOS DE DIFUSIÓN DE LA CAMPAÑA \"CONTAMINACIÓN AMBIENTAL\"","description":"CONTRATACIÓN DE LOS SERVICIOS DE DIFUSIÓN DE LA CAMPAÑA \"CONTAMINACIÓN AMBIENTAL\"","status":"active","value":{"amount":258619.37,"currency":"MXN"},"suppliers":[{"name":"NOTMUSA SA DE CV","id":"NOT011226T29"}],"contractPeriod":{"startDate":"2017-05-04T09:00:00Z","endDate":"2017-08-15T06:00:00Z"}}],"contracts":[{"id":1746626,"awardID":"1746626","title":"CONTRATACIÓN DE LOS SERVICIOS DE DIFUSIÓN DE LA CAMPAÑA \"CONTAMINACIÓN AMBIENTAL\"","description":"CONTRATACIÓN DE LOS SERVICIOS DE DIFUSIÓN DE LA CAMPAÑA \"CONTAMINACIÓN AMBIENTAL\"","status":"terminated","period":{"startDate":"2017-05-04T09:00:00Z","endDate":"2017-08-15T06:00:00Z"},"value":{"amount":258619.37,"currency":"MXN"},"dateSigned":"2017-05-04T00:00:00Z"}]}],"publisher":{"uid":"27511","name":"SECRETARÍA DE LA FUNCIÓN PÚBLICA","uri":"http://www.gob.mx/sfp"}}