{"uri":"http://172.29.100.36:8080/OCDSWS/rest/ocid/ocds-07smqs-1751535","version":"1.1","extensions":["https://raw.githubusercontent.com/CompraNet/ocds_releasePublisher_extension/master/extension.json","https://raw.githubusercontent.com/CompraNet/ocds_schemeUrl_extension/master/extension.json","https://raw.githubusercontent.com/CompraNet/ocds_cycle_extension/master/extension.json"],"publishedDate":"2018-11-12T15:06:56Z","publicationPolicy":"https://compranetinfo.funcionpublica.gob.mx/descargas/politica-publicacion-EDCA-MX.pdf","releases":[{"publisher":{"uid":"27511","name":"SECRETARÍA DE LA FUNCIÓN PÚBLICA","uri":"http://www.gob.mx/sfp"},"cycle":2018,"ocid":"ocds-07smqs-1751535","id":"SFP-1751535-2018-11-12","date":"2018-07-20T05:39:46Z","tag":["tender","award"],"initiationType":"tender","parties":[{"name":"Secretaría de la Función Pública","id":"SFP-270","roles":["buyer"]},{"name":"SFP-Dirección General de Recursos Materiales y Servicios Generales #027000002","id":"SFP941229IMA-027000002","identifier":{"id":"SFP941229IMA-027000002","legalName":"SFP-Dirección General de Recursos Materiales y Servicios Generales #027000002","scheme":"MX-RFC","uri":"https://portalsat.plataforma.sat.gob.mx/ConsultaRFC"},"address":{"streetAddress":"Insurgentes Sur 1735 mezzanine ala sur colonia Guadalupe Inn","locality":"Álvaro Obregón","region":"Ciudad de México","postalCode":"1020","countryName":"MX"},"contactPoint":{"name":"Antonio Omar Fragoso Rodríguez","email":"afragoso@funcionpublica.gob.mx","telephone":"2000-3000 ext 5027"},"roles":["procuringEntity"]},{"name":"TANIA GUZMAN NERI","id":"D24FF8415A2F908D6429539748161C3B","identifier":{"id":"D24FF8415A2F908D6429539748161C3B","legalName":"TANIA GUZMAN NERI","scheme":"MX-RFC","uri":"https://portalsat.plataforma.sat.gob.mx/ConsultaRFC"},"address":{"streetAddress":"Palma azul 24 Rancho la palma","locality":"Coacalco de Berriozábal","region":"MX-MEX","postalCode":"55717","countryName":"MÉXICO"},"contactPoint":{"name":"Tania Guzman Neri","email":"tan_taz1@hotmail.com","telephone":"55-24776831"},"roles":["tenderer","supplier"]}],"buyer":{"name":"Secretaría de la Función Pública","id":"SFP-270"},"tender":{"id":"1751535","title":"CONTRATO DE PRESTACIÓN DE SERVICIOS","description":"CONTRATO DE PRESTACIÓN DE SERVICIOS DE APOYO A LA DIRECCIÓN GENERAL DE DENUNCIAS E INVESTIGACIONES, EN LA INTEGRACIÓN Y ANÁLISIS DE EXPEDIENTES DE INVESTIGACIÓN ASIGNADOS A LAS DIRECCIONES DE INVESTIGACIÓN A, B, C, D, E Y F, ASÍ COMO EN EL DESAHOGO DE LA INVESTIGACIÓN LLEVADA A CABO POR DICHAS DIRECCIONES DE INVESTIGACIÓN, PARA LA DETERMINACIÓN DE FALTAS ADMINISTRATIVAS, ATRIBUIBLES A SERVIDORES PÚBLICOS DE LAS DEPENDENCIAS, LAS ENTIDADES, LA PROCURADURÍA GENERAL DE LA REPÚBLICA, LAS EMPRESAS PRODUCTIVAS DEL ESTADO Y PARTICULARES, POR CONDUCTAS SANCIONABLES EN EL MARCO DE LA LEY GENERAL DE RESPONSABILIDADES ADMINISTRATIVAS, VINCULADO AL 5 AL MILLAR EN TÉRMINOS DEL ARTÍCULO 191 DE LA LEY FEDERAL DE DERECHOS\r\n","status":"complete","procuringEntity":{"name":"SFP-Dirección General de Recursos Materiales y Servicios Generales #027000002","id":"SFP941229IMA-027000002"},"items":[],"value":{"amount":0.0},"procurementMethod":"direct","procurementMethodRationale":"Art. 42 párrafo primero","submissionMethod":["inPerson"],"tenderPeriod":{"startDate":"2018-07-20T05:39:46Z"},"enquiryPeriod":{"startDate":"2018-07-20T05:39:46Z"},"hasEnquiries":false,"awardPeriod":{"endDate":"2018-07-11T00:00:00Z"}},"language":"es","awards":[{"id":"1867451","title":"CONTRATO DE PRESTACIÓN DE SERVICIOS","status":"active","value":{"amount":87999.98,"currency":"MXN"},"suppliers":[{"name":"TANIA GUZMAN NERI","id":"D24FF8415A2F908D6429539748161C3B"}],"contractPeriod":{"startDate":"2018-07-11T12:00:00Z","endDate":"2018-12-20T11:59:00Z"}}],"contracts":[{"id":1867451,"awardID":"1867451","title":"CONTRATO DE PRESTACIÓN DE SERVICIOS","status":"active","period":{"startDate":"2018-07-11T12:00:00Z","endDate":"2018-12-20T11:59:00Z"},"value":{"amount":87999.98,"currency":"MXN"},"dateSigned":"2018-07-25T00:00:00Z"}]}],"publisher":{"uid":"27511","name":"SECRETARÍA DE LA FUNCIÓN PÚBLICA","uri":"http://www.gob.mx/sfp"}}