{"uri":"http://172.29.100.36:8080/OCDSWS/rest/ocid/ocds-07smqs-1756570","version":"1.1","extensions":["https://raw.githubusercontent.com/CompraNet/ocds_releasePublisher_extension/master/extension.json","https://raw.githubusercontent.com/CompraNet/ocds_schemeUrl_extension/master/extension.json","https://raw.githubusercontent.com/CompraNet/ocds_cycle_extension/master/extension.json"],"publishedDate":"2018-11-12T15:26:01Z","publicationPolicy":"https://compranetinfo.funcionpublica.gob.mx/descargas/politica-publicacion-EDCA-MX.pdf","releases":[{"publisher":{"uid":"27511","name":"SECRETARÍA DE LA FUNCIÓN PÚBLICA","uri":"http://www.gob.mx/sfp"},"cycle":2018,"ocid":"ocds-07smqs-1756570","id":"SFP-1756570-2018-11-12","date":"2018-07-26T03:02:48Z","tag":["tender","award"],"initiationType":"tender","parties":[{"name":"Secretaría de Salud","id":"SSA-275","roles":["buyer"]},{"name":"SSA-Dirección General de Recursos Materiales y Servicios Generales/Bienes y Servicios #012000991","id":"SSA630502CU1-012000991","identifier":{"id":"SSA630502CU1-012000991","legalName":"SSA-Dirección General de Recursos Materiales y Servicios Generales/Bienes y Servicios #012000991","scheme":"MX-RFC","uri":"https://portalsat.plataforma.sat.gob.mx/ConsultaRFC"},"address":{"streetAddress":"Avenida Marina Nacional 60, Colonia Tacuba","locality":"Miguel Hidalgo","region":"Ciudad de México","postalCode":"11410","countryName":"MX"},"contactPoint":{"name":"Yasmín del Carmen Arévalo Athié","email":"yasmin.arevalo@salud.gob.mx","telephone":"50621600 Ext. 58304"},"roles":["procuringEntity"]},{"name":"DAN FRANCISCO VAZQUEZ SANABRIA","id":"89F94655D187E614435595C9FAFBBA46","identifier":{"id":"89F94655D187E614435595C9FAFBBA46","legalName":"DAN FRANCISCO VAZQUEZ SANABRIA","scheme":"MX-RFC","uri":"https://portalsat.plataforma.sat.gob.mx/ConsultaRFC"},"address":{"streetAddress":"ORIENTE 154 #279 COL. MOCTEZUMA 2DA. SECC.","locality":"VENUSTIANO CARRANZA","region":"MX-CMX","postalCode":"15530","countryName":"MÉXICO"},"contactPoint":{"name":"DAN FRANCISCO VAZQUEZ SANABRIA","email":"fvazquez2000@hotmail.com","telephone":"01 55 55719223","faxNumber":"01 55 55719223"},"roles":["tenderer","supplier"]}],"buyer":{"name":"Secretaría de Salud","id":"SSA-275"},"tender":{"id":"1756570","title":"SERVICIO DE MANTENIMIENTO PREVENTIVO A EQUIPO PARA HISTEROSCOPIA Y GINECOLOGÍA L","description":"SERVICIO DE MANTENIMIENTO PREVENTIVO A EQUIPO PARA HISTEROSCOPIA Y GINECOLOGÍA LAPAROSCOPICA","status":"complete","procuringEntity":{"name":"SSA-Dirección General de Recursos Materiales y Servicios Generales/Bienes y Servicios #012000991","id":"SSA630502CU1-012000991"},"items":[],"value":{"amount":0.0},"procurementMethod":"direct","procurementMethodRationale":"Art. 42 párrafo segundo","submissionMethod":["inPerson"],"tenderPeriod":{"startDate":"2018-07-26T03:02:48Z"},"enquiryPeriod":{"startDate":"2018-07-26T03:02:48Z"},"hasEnquiries":false,"awardPeriod":{"endDate":"2018-07-13T00:00:00Z"}},"language":"es","awards":[{"id":"1872827","title":"SERVICIO DE MANTENIMIENTO PREVENTIVO A EQUIPO PARA HISTEROSCOPIA Y GINECOLOGÍA LAPAROSCOPICA","description":"SERVICIO DE MANTENIMIENTO PREVENTIVO A EQUIPO PARA HISTEROSCOPIA Y GINECOLOGÍA LAPAROSCOPICA","status":"active","value":{"amount":260000.0,"currency":"MXN"},"suppliers":[{"name":"DAN FRANCISCO VAZQUEZ SANABRIA","id":"89F94655D187E614435595C9FAFBBA46"}],"contractPeriod":{"startDate":"2018-07-14T12:00:00Z","endDate":"2018-12-31T11:59:00Z"}}],"contracts":[{"id":1872827,"awardID":"1872827","title":"SERVICIO DE MANTENIMIENTO PREVENTIVO A EQUIPO PARA HISTEROSCOPIA Y GINECOLOGÍA LAPAROSCOPICA","description":"SERVICIO DE MANTENIMIENTO PREVENTIVO A EQUIPO PARA HISTEROSCOPIA Y GINECOLOGÍA LAPAROSCOPICA","status":"active","period":{"startDate":"2018-07-14T12:00:00Z","endDate":"2018-12-31T11:59:00Z"},"value":{"amount":260000.0,"currency":"MXN"}}]}],"publisher":{"uid":"27511","name":"SECRETARÍA DE LA FUNCIÓN PÚBLICA","uri":"http://www.gob.mx/sfp"}}