{"uri":"http://172.29.100.36:8080/OCDSWS/rest/ocid/ocds-07smqs-1784602","version":"1.1","extensions":["https://raw.githubusercontent.com/CompraNet/ocds_releasePublisher_extension/master/extension.json","https://raw.githubusercontent.com/CompraNet/ocds_schemeUrl_extension/master/extension.json","https://raw.githubusercontent.com/CompraNet/ocds_cycle_extension/master/extension.json"],"publishedDate":"2018-11-12T15:31:54Z","publicationPolicy":"https://compranetinfo.funcionpublica.gob.mx/descargas/politica-publicacion-EDCA-MX.pdf","releases":[{"publisher":{"uid":"27511","name":"SECRETARÍA DE LA FUNCIÓN PÚBLICA","uri":"http://www.gob.mx/sfp"},"cycle":2018,"ocid":"ocds-07smqs-1784602","id":"SFP-1784602-2018-11-12","date":"2018-08-29T12:30:11Z","tag":["tender","award"],"initiationType":"tender","parties":[{"name":"Coordinación Nacional de PROSPERA Programa de Inclusión Social","id":"PROSPERA-117","roles":["buyer"]},{"name":"PROSPERA-Delegación Estatal en Quintana Roo #020G00970","id":"CNP140906H36-020G00970","identifier":{"id":"CNP140906H36-020G00970","legalName":"PROSPERA-Delegación Estatal en Quintana Roo #020G00970","scheme":"MX-RFC","uri":"https://portalsat.plataforma.sat.gob.mx/ConsultaRFC"},"address":{"streetAddress":"Av. Carmen Ochoa de Merino No. 162","locality":"Othón P. Blanco","region":"Quintana Roo","postalCode":"77000","countryName":"MX"},"contactPoint":{"name":"Krizia Massiel Dorantes Magaña","email":"ce_qroo@prospera.gob.mx","telephone":"9838325419"},"roles":["procuringEntity"]},{"name":"SANDRA CONSUELO ARRIAGA RODELO","id":"881E78CE739C93AD091DB91E6BD1E9A4","identifier":{"id":"881E78CE739C93AD091DB91E6BD1E9A4","legalName":"SANDRA CONSUELO ARRIAGA RODELO","scheme":"MX-RFC","uri":"https://portalsat.plataforma.sat.gob.mx/ConsultaRFC"},"address":{"streetAddress":"MIGUEL ECHEGARAY 78 CHAPULTEPEC ORIENTE","locality":"Morelia","region":"MX-MIC","postalCode":"58260","countryName":"MÉXICO"},"contactPoint":{"name":"SANDRA CONSUELO ARRIAGA RODELO","email":"arriagagano@gmail.com","telephone":"4433570752","faxNumber":"4433570752"},"roles":["tenderer","supplier"]}],"buyer":{"name":"Coordinación Nacional de PROSPERA Programa de Inclusión Social","id":"PROSPERA-117"},"tender":{"id":"1784602","title":"ARRENDAMIENTO DE MOBILIARIO","description":"ARRENDAMIENTO DE MOBILIARIO","status":"complete","procuringEntity":{"name":"PROSPERA-Delegación Estatal en Quintana Roo #020G00970","id":"CNP140906H36-020G00970"},"items":[],"value":{"amount":0.0},"procurementMethod":"direct","procurementMethodRationale":"Art. 42 párrafo primero","submissionMethod":["electronicSubmission"],"tenderPeriod":{"startDate":"2018-08-29T12:30:11Z"},"enquiryPeriod":{"startDate":"2018-08-29T12:30:11Z"},"hasEnquiries":false,"awardPeriod":{"endDate":"2018-07-09T00:00:00Z"}},"language":"es","awards":[{"id":"1911559","title":"ARRENDAMIENTO DE MOBILIARIO","description":"ARRENDAMIENTO DE MOBILIARIO","status":"active","value":{"amount":25862.02,"currency":"MXN"},"suppliers":[{"name":"SANDRA CONSUELO ARRIAGA RODELO","id":"881E78CE739C93AD091DB91E6BD1E9A4"}],"contractPeriod":{"startDate":"2018-07-09T12:00:00Z","endDate":"2018-07-19T11:59:00Z"}}],"contracts":[{"id":1911559,"awardID":"1911559","title":"ARRENDAMIENTO DE MOBILIARIO","description":"ARRENDAMIENTO DE MOBILIARIO","status":"terminated","period":{"startDate":"2018-07-09T12:00:00Z","endDate":"2018-07-19T11:59:00Z"},"value":{"amount":25862.02,"currency":"MXN"}}]}],"publisher":{"uid":"27511","name":"SECRETARÍA DE LA FUNCIÓN PÚBLICA","uri":"http://www.gob.mx/sfp"}}