{"uri":"http://172.29.100.36:8080/OCDSWS/rest/ocid/ocds-07smqs-1793112","version":"1.1","extensions":["https://raw.githubusercontent.com/CompraNet/ocds_releasePublisher_extension/master/extension.json","https://raw.githubusercontent.com/CompraNet/ocds_schemeUrl_extension/master/extension.json","https://raw.githubusercontent.com/CompraNet/ocds_cycle_extension/master/extension.json"],"publishedDate":"2018-11-12T15:31:28Z","publicationPolicy":"https://compranetinfo.funcionpublica.gob.mx/descargas/politica-publicacion-EDCA-MX.pdf","releases":[{"publisher":{"uid":"27511","name":"SECRETARÍA DE LA FUNCIÓN PÚBLICA","uri":"http://www.gob.mx/sfp"},"cycle":2018,"ocid":"ocds-07smqs-1793112","id":"SFP-1793112-2018-11-12","date":"2018-09-12T07:43:44Z","tag":["tender","award"],"initiationType":"tender","parties":[{"name":"Secretaría de Desarrollo Agrario, Territorial y Urbano","id":"SEDATU-271","roles":["buyer"]},{"name":"SEDATU-Dirección General de Recursos Materiales y Servicios Generales #015000999","id":"SRA750101RB7-015000999","identifier":{"id":"SRA750101RB7-015000999","legalName":"SEDATU-Dirección General de Recursos Materiales y Servicios Generales #015000999","scheme":"MX-RFC","uri":"https://portalsat.plataforma.sat.gob.mx/ConsultaRFC"},"address":{"streetAddress":"Av. Heroica Escuela Naval Militar No. 701, Col. Presidentes Ejidales, segunda sección.","locality":"Coyoacán","region":"Ciudad de México","postalCode":"04470","countryName":"MX"},"contactPoint":{"name":"Humberto René Islas Cortés","email":"rene.islas@sedatu.gob.mx","telephone":"36013000  "},"roles":["procuringEntity"]},{"name":"GERARDO DANIEL BOLAÑOS MARTINEZ","id":"11F8BE23E2C9F760B292AD2528985F88","identifier":{"id":"11F8BE23E2C9F760B292AD2528985F88","legalName":"GERARDO DANIEL BOLAÑOS MARTINEZ","scheme":"MX-RFC","uri":"https://portalsat.plataforma.sat.gob.mx/ConsultaRFC"},"address":{"locality":"CHALCO DE DIAZ COVARRUBIAS","region":"MX-MEX","countryName":"MÉXICO"},"contactPoint":{"name":"- (Cuenta administrada por \u0027SEDATU-Dirección General de Recursos Materiales y Servicios Generales #015000999\u0027)","email":"sergio.rodriguez@sedatu.gob.mx"},"roles":["tenderer","supplier"]}],"buyer":{"name":"Secretaría de Desarrollo Agrario, Territorial y Urbano","id":"SEDATU-271"},"tender":{"id":"1793112","title":"PRESTADOR DE SERVICIOS PROFESIONALES ","description":"PRESTADOR DE SERVICIOS PROFESIONALES","status":"complete","procuringEntity":{"name":"SEDATU-Dirección General de Recursos Materiales y Servicios Generales #015000999","id":"SRA750101RB7-015000999"},"items":[],"value":{"amount":0.0},"procurementMethod":"direct","procurementMethodRationale":"Art. 41 fr. XIV","submissionMethod":["electronicSubmission"],"tenderPeriod":{"startDate":"2018-09-12T07:43:44Z"},"enquiryPeriod":{"startDate":"2018-09-12T07:43:44Z"},"hasEnquiries":false,"awardPeriod":{"endDate":"2018-02-09T00:00:00Z"}},"language":"es","awards":[{"id":"1924627","title":"PRESTADOR DE SERVICIOS PROFESIONALES","description":"PRESTADOR DE SERVICIOS PROFESIONALES","status":"active","value":{"amount":31468.53,"currency":"MXN"},"suppliers":[{"name":"GERARDO DANIEL BOLAÑOS MARTINEZ","id":"11F8BE23E2C9F760B292AD2528985F88"}],"contractPeriod":{"startDate":"2018-02-09T12:00:00Z","endDate":"2018-02-28T11:59:00Z"}}],"contracts":[{"id":1924627,"awardID":"1924627","title":"PRESTADOR DE SERVICIOS PROFESIONALES","description":"PRESTADOR DE SERVICIOS PROFESIONALES","status":"terminated","period":{"startDate":"2018-02-09T12:00:00Z","endDate":"2018-02-28T11:59:00Z"},"value":{"amount":31468.53,"currency":"MXN"}}]}],"publisher":{"uid":"27511","name":"SECRETARÍA DE LA FUNCIÓN PÚBLICA","uri":"http://www.gob.mx/sfp"}}