{"uri":"http://172.29.100.36:8080/OCDSWS/rest/ocid/ocds-07smqs-1795091","version":"1.1","extensions":["https://raw.githubusercontent.com/CompraNet/ocds_releasePublisher_extension/master/extension.json","https://raw.githubusercontent.com/CompraNet/ocds_schemeUrl_extension/master/extension.json","https://raw.githubusercontent.com/CompraNet/ocds_cycle_extension/master/extension.json"],"publishedDate":"2018-11-12T15:30:10Z","publicationPolicy":"https://compranetinfo.funcionpublica.gob.mx/descargas/politica-publicacion-EDCA-MX.pdf","releases":[{"publisher":{"uid":"27511","name":"SECRETARÍA DE LA FUNCIÓN PÚBLICA","uri":"http://www.gob.mx/sfp"},"cycle":2018,"ocid":"ocds-07smqs-1795091","id":"SFP-1795091-2018-11-12","date":"2018-09-19T05:47:48Z","tag":["tender","award"],"initiationType":"tender","parties":[{"name":"Secretaría de Medio Ambiente y Recursos Naturales","id":"SEMARNAT-273","roles":["buyer"]},{"name":"SEMARNAT-Dirección de Adquisiciones y Contratos #016000997","id":"SMA941228GU8-016000997","identifier":{"id":"SMA941228GU8-016000997","legalName":"SEMARNAT-Dirección de Adquisiciones y Contratos #016000997","scheme":"MX-RFC","uri":"https://portalsat.plataforma.sat.gob.mx/ConsultaRFC"},"address":{"streetAddress":"Ejército Nacional No. 223, Col. Anáhuac","locality":"Miguel Hidalgo","region":"Ciudad de México","postalCode":"11350","countryName":"MX"},"contactPoint":{"name":"Elvia Patricia Bañuelos Solano","email":"patricia.banuelo@semarnat.gob.mx","telephone":"55 56280600 ext. 25848"},"roles":["procuringEntity"]},{"name":"TRANS-COMUNICACION SA DE CV","id":"TRA1201314F1","identifier":{"id":"TRA1201314F1","legalName":"TRANS-COMUNICACION SA DE CV","scheme":"MX-RFC","uri":"https://portalsat.plataforma.sat.gob.mx/ConsultaRFC"},"address":{"streetAddress":"CALZADA VALLEJO No. 705, COLONIA NUEVA VALLEJO","locality":"GUSTAVO A. MADERO","region":"MX-CMX","postalCode":"07750","countryName":"MÉXICO"},"contactPoint":{"name":"ALEJANDRO LOYDA ROMAN","email":"josemiguel@otesa.net","telephone":"(01 55) 53 68 13 77        EXT. 117"},"roles":["tenderer","supplier"]}],"buyer":{"name":"Secretaría de Medio Ambiente y Recursos Naturales","id":"SEMARNAT-273"},"tender":{"id":"1795091","title":"CAMPAÑA “PROTECCIÓN DE LOS OCÉANOS. VERSIÓN: MARES Y COSTAS DE MÉXICO”","description":"CAMPAÑA “PROTECCIÓN DE LOS OCÉANOS. VERSIÓN: MARES Y COSTAS DE MÉXICO”","status":"complete","procuringEntity":{"name":"SEMARNAT-Dirección de Adquisiciones y Contratos #016000997","id":"SMA941228GU8-016000997"},"items":[],"value":{"amount":0.0},"procurementMethod":"direct","procurementMethodRationale":"Art. 41 fr. I","submissionMethod":["inPerson"],"tenderPeriod":{"startDate":"2018-09-19T05:47:48Z"},"enquiryPeriod":{"startDate":"2018-09-19T05:47:48Z"},"hasEnquiries":false,"awardPeriod":{"endDate":"2018-08-30T00:00:00Z"}},"language":"es","awards":[{"id":"1927428","title":"CAMPAÑA “PROTECCIÓN DE LOS OCÉANOS. VERSIÓN: MARES Y COSTAS DE MÉXICO”","description":"CAMPAÑA “PROTECCIÓN DE LOS OCÉANOS. VERSIÓN: MARES Y COSTAS DE MÉXICO”\r\nCONTRATO ABIERTO\r\nIMPORTE MÍNIMO SIN I.V.A. $2,326,992.07\r\nIMPORTE MÁXIMO SIN I.V.A. $2,585,546.74","status":"active","value":{"amount":2585546.74,"currency":"MXN"},"suppliers":[{"name":"TRANS-COMUNICACION SA DE CV","id":"TRA1201314F1"}],"contractPeriod":{"startDate":"2018-08-30T06:00:00Z","endDate":"2018-12-31T06:00:00Z"}}],"contracts":[{"id":1927428,"awardID":"1927428","title":"CAMPAÑA “PROTECCIÓN DE LOS OCÉANOS. VERSIÓN: MARES Y COSTAS DE MÉXICO”","description":"CAMPAÑA “PROTECCIÓN DE LOS OCÉANOS. VERSIÓN: MARES Y COSTAS DE MÉXICO”\r\nCONTRATO ABIERTO\r\nIMPORTE MÍNIMO SIN I.V.A. $2,326,992.07\r\nIMPORTE MÁXIMO SIN I.V.A. $2,585,546.74","status":"active","period":{"startDate":"2018-08-30T06:00:00Z","endDate":"2018-12-31T06:00:00Z"},"value":{"amount":2585546.74,"currency":"MXN"},"dateSigned":"2018-09-14T00:00:00Z"}]}],"publisher":{"uid":"27511","name":"SECRETARÍA DE LA FUNCIÓN PÚBLICA","uri":"http://www.gob.mx/sfp"}}